[
  {
    "Type": "BlendSpace1D",
    "Name": "BS_WeatherStation_Horizontal",
    "Class": "UScriptClass'BlendSpace1D'",
    "Properties": {
      "SampleData": [
        {
          "Animation": {
            "ObjectName": "AnimSequence'ANIM_WeatherStation_POSE_horizontal_0'",
            "ObjectPath": "War/Content/Animation/WorldAssets/Fort_and_Trenches/WeatherStation/ANIM_WeatherStation_POSE_horizontal_0.0"
          },
          "SampleValue": {
            "X": 0.0,
            "Y": 0.0,
            "Z": 0.0
          },
          "RateScale": 1.0
        },
        {
          "Animation": {
            "ObjectName": "AnimSequence'ANIM_WeatherStation_POSE_horizontal_180'",
            "ObjectPath": "War/Content/Animation/WorldAssets/Fort_and_Trenches/WeatherStation/ANIM_WeatherStation_POSE_horizontal_180.0"
          },
          "SampleValue": {
            "X": 180.0,
            "Y": 0.0,
            "Z": 0.0
          },
          "RateScale": 1.0
        },
        {
          "Animation": {
            "ObjectName": "AnimSequence'ANIM_WeatherStation_POSE_horizontal_180'",
            "ObjectPath": "War/Content/Animation/WorldAssets/Fort_and_Trenches/WeatherStation/ANIM_WeatherStation_POSE_horizontal_180.0"
          },
          "SampleValue": {
            "X": -180.0,
            "Y": 0.0,
            "Z": 0.0
          },
          "RateScale": 1.0
        },
        {
          "Animation": {
            "ObjectName": "AnimSequence'ANIM_WeatherStation_POSE_horizontal_270'",
            "ObjectPath": "War/Content/Animation/WorldAssets/Fort_and_Trenches/WeatherStation/ANIM_WeatherStation_POSE_horizontal_270.0"
          },
          "SampleValue": {
            "X": 90.0,
            "Y": 0.0,
            "Z": 0.0
          },
          "RateScale": 1.0
        },
        {
          "Animation": {
            "ObjectName": "AnimSequence'ANIM_WeatherStation_POSE_horizontal_90'",
            "ObjectPath": "War/Content/Animation/WorldAssets/Fort_and_Trenches/WeatherStation/ANIM_WeatherStation_POSE_horizontal_90.0"
          },
          "SampleValue": {
            "X": -90.0,
            "Y": 0.0,
            "Z": 0.0
          },
          "RateScale": 1.0
        }
      ],
      "GridSamples": [
        {
          "Indices": 4,
          "Indices": 2,
          "Indices": -1,
          "Weights": 0.0,
          "Weights": 1.0,
          "Weights": 0.0
        },
        {
          "Indices": 4,
          "Indices": 2,
          "Indices": -1,
          "Weights": 1.0,
          "Weights": 0.0,
          "Weights": 0.0
        },
        {
          "Indices": 0,
          "Indices": 4,
          "Indices": -1,
          "Weights": 1.0,
          "Weights": 0.0,
          "Weights": 0.0
        },
        {
          "Indices": 3,
          "Indices": 0,
          "Indices": -1,
          "Weights": 1.0,
          "Weights": 0.0,
          "Weights": 0.0
        },
        {
          "Indices": 1,
          "Indices": 3,
          "Indices": -1,
          "Weights": 1.0,
          "Weights": 0.0,
          "Weights": 0.0
        }
      ],
      "BlendParameters": {
        "DisplayName": "Yaw",
        "Min": -180.0,
        "Max": 180.0
      },
      "Skeleton": {
        "ObjectName": "Skeleton'SK_WeatherStation_upper_Skeleton'",
        "ObjectPath": "War/Content/Animation/WorldAssets/Fort_and_Trenches/WeatherStation/SK_WeatherStation_upper_Skeleton.1"
      }
    },
    "SkeletonGuid": "0B1DCE42-4D936F16-4FAC73B5-3AD35EDD"
  }
]