[
  {
    "Type": "SoundWave",
    "Name": "Swim05",
    "Class": "UScriptClass'SoundWave'",
    "Flags": "RF_Public | RF_Standalone | RF_Transactional | RF_WasLoaded | RF_LoadCompleted",
    "Properties": {
      "NumChannels": 1,
      "SampleRate": 44100,
      "Duration": 0.9527891
    },
    "CompressedFormatData": {
      "OGG10025600-1-1-1-1-1": {
        "BulkDataFlags": "BULKDATA_SingleUse | BULKDATA_ForceInlinePayload",
        "ElementCount": 15736,
        "SizeOnDisk": 15736,
        "OffsetInFile": "0x43C4"
      }
    },
    "RawData": null,
    "CompressedDataGuid": "5A2455C5-41CAF5BD-6C19D595-14212D3E",
    "RunningPlatformData": null
  }
]