[
  {
    "Type": "BodySetup",
    "Name": "BodySetup_1",
    "Outer": "TownCSmallG2",
    "Class": "UScriptClass'BodySetup'",
    "Properties": {
      "AggGeom": {
        "ConvexElems": [
          {
            "VertexData": [
              {
                "X": 20.86145,
                "Y": 584.1347,
                "Z": -240.3911
              },
              {
                "X": 793.0532,
                "Y": 584.1347,
                "Z": -240.3911
              },
              {
                "X": 20.86145,
                "Y": -6.0538025,
                "Z": -240.3911
              },
              {
                "X": 793.0532,
                "Y": -6.0538025,
                "Z": -240.3911
              },
              {
                "X": 20.86145,
                "Y": 584.1347,
                "Z": 483.17435
              },
              {
                "X": 793.0532,
                "Y": 584.1347,
                "Z": 484.02515
              },
              {
                "X": 20.86145,
                "Y": -6.0538025,
                "Z": 483.17435
              },
              {
                "X": 793.0532,
                "Y": -6.0538025,
                "Z": 484.02515
              },
              {
                "X": 509.5253,
                "Y": -6.0538025,
                "Z": -240.3911
              },
              {
                "X": 509.5253,
                "Y": 584.1347,
                "Z": -240.3911
              },
              {
                "X": 509.5253,
                "Y": 584.1347,
                "Z": 648.666
              },
              {
                "X": 509.5253,
                "Y": -6.053772,
                "Z": 648.666
              }
            ],
            "ElemBox": {
              "Min": {
                "X": 20.86145,
                "Y": -6.0538025,
                "Z": -240.3911
              },
              "Max": {
                "X": 793.0532,
                "Y": 584.1347,
                "Z": 648.666
              },
              "IsValid": 1
            },
            "Transform": {
              "Rotation": {
                "X": 0.0,
                "Y": 0.0,
                "Z": 0.0,
                "W": 1.0,
                "IsNormalized": true,
                "Size": 1.0,
                "SizeSquared": 1.0
              },
              "Translation": {
                "X": 0.0,
                "Y": 0.0,
                "Z": 0.0
              },
              "Scale3D": {
                "X": 1.0,
                "Y": 1.0,
                "Z": 1.0
              }
            },
            "RestOffset": 0.0,
            "Name": "None",
            "bContributeToMass": true
          },
          {
            "VertexData": [
              {
                "X": 71.55722,
                "Y": 387.68835,
                "Z": 490.13
              },
              {
                "X": 71.55722,
                "Y": 207.47772,
                "Z": 490.13
              },
              {
                "X": 71.55722,
                "Y": 387.68835,
                "Z": 643.90936
              },
              {
                "X": 71.55722,
                "Y": 207.47772,
                "Z": 643.90936
              },
              {
                "X": 479.27737,
                "Y": 387.68835,
                "Z": 490.13
              },
              {
                "X": 479.27737,
                "Y": 207.47772,
                "Z": 490.13
              },
              {
                "X": 479.27737,
                "Y": 207.47772,
                "Z": 642.348
              },
              {
                "X": 479.27737,
                "Y": 387.68835,
                "Z": 642.348
              }
            ],
            "ElemBox": {
              "Min": {
                "X": 71.55722,
                "Y": 207.47772,
                "Z": 490.13
              },
              "Max": {
                "X": 479.27737,
                "Y": 387.68835,
                "Z": 643.90936
              },
              "IsValid": 1
            },
            "Transform": {
              "Rotation": {
                "X": 0.0,
                "Y": 0.0,
                "Z": 0.0,
                "W": 1.0,
                "IsNormalized": true,
                "Size": 1.0,
                "SizeSquared": 1.0
              },
              "Translation": {
                "X": 0.0,
                "Y": 0.0,
                "Z": 0.0
              },
              "Scale3D": {
                "X": 1.0,
                "Y": 1.0,
                "Z": 1.0
              }
            },
            "RestOffset": 0.0,
            "Name": "None",
            "bContributeToMass": true
          },
          {
            "VertexData": [
              {
                "X": 333.71115,
                "Y": 581.65295,
                "Z": -240.39107
              },
              {
                "X": 333.71115,
                "Y": 527.21545,
                "Z": -240.3911
              },
              {
                "X": 676.98804,
                "Y": 527.21545,
                "Z": -240.39111
              },
              {
                "X": 676.98804,
                "Y": 581.65295,
                "Z": -240.39107
              },
              {
                "X": 333.71115,
                "Y": 581.6529,
                "Z": 68.61998
              },
              {
                "X": 676.98804,
                "Y": 581.6529,
                "Z": 67.05855
              },
              {
                "X": 676.98804,
                "Y": 527.21545,
                "Z": 67.05855
              },
              {
                "X": 333.71115,
                "Y": 527.21545,
                "Z": 68.61998
              },
              {
                "X": 333.71115,
                "Y": 736.2005,
                "Z": -240.39104
              },
              {
                "X": 676.98804,
                "Y": 736.2005,
                "Z": -240.39104
              },
              {
                "X": 676.98804,
                "Y": 736.20044,
                "Z": -62.530167
              },
              {
                "X": 333.71115,
                "Y": 736.20044,
                "Z": -60.968735
              }
            ],
            "ElemBox": {
              "Min": {
                "X": 333.71115,
                "Y": 527.21545,
                "Z": -240.39111
              },
              "Max": {
                "X": 676.98804,
                "Y": 736.2005,
                "Z": 68.61998
              },
              "IsValid": 1
            },
            "Transform": {
              "Rotation": {
                "X": 0.0,
                "Y": 0.0,
                "Z": 0.0,
                "W": 1.0,
                "IsNormalized": true,
                "Size": 1.0,
                "SizeSquared": 1.0
              },
              "Translation": {
                "X": 0.0,
                "Y": 0.0,
                "Z": 0.0
              },
              "Scale3D": {
                "X": 1.0,
                "Y": 1.0,
                "Z": 1.0
              }
            },
            "RestOffset": 0.0,
            "Name": "None",
            "bContributeToMass": true
          },
          {
            "VertexData": [
              {
                "X": -58.2446,
                "Y": 610.4697,
                "Z": 464.2833
              },
              {
                "X": 509.49002,
                "Y": 610.4697,
                "Z": 653.21484
              },
              {
                "X": 509.49002,
                "Y": -93.72522,
                "Z": 653.21484
              },
              {
                "X": -58.2446,
                "Y": -93.72525,
                "Z": 464.2833
              },
              {
                "X": -54.817963,
                "Y": 610.4697,
                "Z": 454.88876
              },
              {
                "X": 509.56058,
                "Y": 610.4697,
                "Z": 643.8203
              },
              {
                "X": 509.56058,
                "Y": -93.72522,
                "Z": 643.8203
              },
              {
                "X": -54.817963,
                "Y": -93.72525,
                "Z": 454.88876
              }
            ],
            "ElemBox": {
              "Min": {
                "X": -58.2446,
                "Y": -93.72525,
                "Z": 454.88876
              },
              "Max": {
                "X": 509.56058,
                "Y": 610.4697,
                "Z": 653.21484
              },
              "IsValid": 1
            },
            "Transform": {
              "Rotation": {
                "X": 0.0,
                "Y": 0.0,
                "Z": 0.0,
                "W": 1.0,
                "IsNormalized": true,
                "Size": 1.0,
                "SizeSquared": 1.0
              },
              "Translation": {
                "X": 0.0,
                "Y": 0.0,
                "Z": 0.0
              },
              "Scale3D": {
                "X": 1.0,
                "Y": 1.0,
                "Z": 1.0
              }
            },
            "RestOffset": 0.0,
            "Name": "None",
            "bContributeToMass": true
          },
          {
            "VertexData": [
              {
                "X": 817.3141,
                "Y": 610.4697,
                "Z": 475.74158
              },
              {
                "X": 817.3141,
                "Y": -93.72525,
                "Z": 475.74158
              },
              {
                "X": 509.5827,
                "Y": 610.4697,
                "Z": 653.3952
              },
              {
                "X": 509.5827,
                "Y": -93.72522,
                "Z": 653.3952
              },
              {
                "X": 811.74133,
                "Y": 610.4697,
                "Z": 467.43835
              },
              {
                "X": 811.74133,
                "Y": -93.72525,
                "Z": 467.43835
              },
              {
                "X": 509.4679,
                "Y": 610.4697,
                "Z": 645.092
              },
              {
                "X": 509.4679,
                "Y": -93.72522,
                "Z": 645.092
              }
            ],
            "ElemBox": {
              "Min": {
                "X": 509.4679,
                "Y": -93.72525,
                "Z": 467.43835
              },
              "Max": {
                "X": 817.3141,
                "Y": 610.4697,
                "Z": 653.3952
              },
              "IsValid": 1
            },
            "Transform": {
              "Rotation": {
                "X": 0.0,
                "Y": 0.0,
                "Z": 0.0,
                "W": 1.0,
                "IsNormalized": true,
                "Size": 1.0,
                "SizeSquared": 1.0
              },
              "Translation": {
                "X": 0.0,
                "Y": 0.0,
                "Z": 0.0
              },
              "Scale3D": {
                "X": 1.0,
                "Y": 1.0,
                "Z": 1.0
              }
            },
            "RestOffset": 0.0,
            "Name": "None",
            "bContributeToMass": true
          }
        ]
      },
      "DefaultInstance": {
        "ObjectType": "ECC_WorldStatic",
        "CollisionProfileName": "BlockAll",
        "CollisionResponses": {
          "ResponseArray": [
            {
              "Channel": "Damage",
              "Response": "ECR_Overlap"
            }
          ]
        }
      }
    },
    "BodySetupGuid": "0540DDA042E23630876F30B7D00800CF",
    "CookedFormatData": {
      "PhysXPC": {
        "BulkDataFlags": "BULKDATA_SingleUse | BULKDATA_ForceInlinePayload",
        "ElementCount": 264261,
        "SizeOnDisk": 264261,
        "OffsetInFile": "0x11615F"
      }
    }
  },
  {
    "Type": "NavCollision",
    "Name": "NavCollision_1",
    "Outer": "TownCSmallG2",
    "Class": "UScriptClass'NavCollision'",
    "CookedFormatData": {
      "NavCollision_X": {
        "BulkDataFlags": "BULKDATA_SingleUse | BULKDATA_ForceInlinePayload",
        "ElementCount": 2441,
        "SizeOnDisk": 2441,
        "OffsetInFile": "0x1569EC"
      }
    }
  },
  {
    "Type": "StaticMesh",
    "Name": "TownCSmallG2",
    "Class": "UScriptClass'StaticMesh'",
    "Properties": {
      "StaticMaterials": [
        {
          "MaterialInterface": {
            "ObjectName": "MaterialInstanceConstant'SouthRoofShingles01'",
            "ObjectPath": "War/Content/Materials/Environment/Town/SouthRoofShingles01.0"
          },
          "MaterialSlotName": "Shingles",
          "ImportedMaterialSlotName": "Shingles",
          "UVChannelData": {
            "bInitialized": true,
            "bOverrideDensities": false,
            "LocalUVDensities": 188.8379,
            "LocalUVDensities": 0.0,
            "LocalUVDensities": 1.0780867,
            "LocalUVDensities": 0.0
          }
        },
        {
          "MaterialInterface": {
            "ObjectName": "MaterialInstanceConstant'SouthPlaster01'",
            "ObjectPath": "War/Content/Materials/Environment/Town/SouthPlaster01.0"
          },
          "MaterialSlotName": "Plaster",
          "ImportedMaterialSlotName": "Plaster",
          "UVChannelData": {
            "bInitialized": true,
            "bOverrideDensities": false,
            "LocalUVDensities": 301.61926,
            "LocalUVDensities": 0.0,
            "LocalUVDensities": 1.1111394,
            "LocalUVDensities": 0.0
          }
        },
        {
          "MaterialInterface": {
            "ObjectName": "MaterialInstanceConstant'SouthDoors'",
            "ObjectPath": "War/Content/Materials/Environment/Town/SouthDoors.0"
          },
          "MaterialSlotName": "Door",
          "ImportedMaterialSlotName": "SouthDoors",
          "UVChannelData": {
            "bInitialized": true,
            "bOverrideDensities": false,
            "LocalUVDensities": 248.1173,
            "LocalUVDensities": 0.0,
            "LocalUVDensities": 0.0,
            "LocalUVDensities": 0.0
          }
        },
        {
          "MaterialInterface": {
            "ObjectName": "MaterialInstanceConstant'SouthTileOutdoor'",
            "ObjectPath": "War/Content/Materials/Environment/Town/SouthTileOutdoor.0"
          },
          "MaterialSlotName": "Tile",
          "ImportedMaterialSlotName": "Tile",
          "UVChannelData": {
            "bInitialized": true,
            "bOverrideDensities": false,
            "LocalUVDensities": 300.31372,
            "LocalUVDensities": 0.0,
            "LocalUVDensities": 3.1602662,
            "LocalUVDensities": 0.0
          }
        },
        {
          "MaterialInterface": {
            "ObjectName": "MaterialInstanceConstant'FortT2WoodBeam01'",
            "ObjectPath": "War/Content/Materials/Structures/FortT2WoodBeam01.0"
          },
          "MaterialSlotName": "Wood",
          "ImportedMaterialSlotName": "Floor",
          "UVChannelData": {
            "bInitialized": true,
            "bOverrideDensities": false,
            "LocalUVDensities": 311.0632,
            "LocalUVDensities": 0.0,
            "LocalUVDensities": 1.4382905,
            "LocalUVDensities": 0.0
          }
        },
        {
          "MaterialInterface": {
            "ObjectName": "MaterialInstanceConstant'SouthBrick'",
            "ObjectPath": "War/Content/Materials/Environment/Town/SouthBrick.0"
          },
          "MaterialSlotName": "SouthBrick",
          "ImportedMaterialSlotName": "SouthBrick",
          "UVChannelData": {
            "bInitialized": true,
            "bOverrideDensities": false,
            "LocalUVDensities": 299.868,
            "LocalUVDensities": 0.0,
            "LocalUVDensities": 1.0003976,
            "LocalUVDensities": 0.0
          }
        },
        {
          "MaterialInterface": {
            "ObjectName": "MaterialInstanceConstant'TrenchDirtTile'",
            "ObjectPath": "War/Content/Materials/Environment/TrenchDirtTile.0"
          },
          "MaterialSlotName": "DirtBase",
          "ImportedMaterialSlotName": "DirtBase",
          "UVChannelData": {
            "bInitialized": true,
            "bOverrideDensities": false,
            "LocalUVDensities": 300.0788,
            "LocalUVDensities": 0.0,
            "LocalUVDensities": 60.19125,
            "LocalUVDensities": 0.0
          }
        },
        {
          "MaterialInterface": {
            "ObjectName": "MaterialInstanceConstant'SouthTrim02'",
            "ObjectPath": "War/Content/Materials/Environment/Town/SouthTrim02.0"
          },
          "MaterialSlotName": "SouthTrim02",
          "ImportedMaterialSlotName": "SouthTrim02",
          "UVChannelData": {
            "bInitialized": true,
            "bOverrideDensities": false,
            "LocalUVDensities": 792.81396,
            "LocalUVDensities": 0.0,
            "LocalUVDensities": 0.0,
            "LocalUVDensities": 0.0
          }
        },
        {
          "MaterialInterface": {
            "ObjectName": "Material'WorldGridMaterial'",
            "ObjectPath": "Engine/Content/EngineMaterials/WorldGridMaterial.0"
          },
          "MaterialSlotName": "Material #26",
          "ImportedMaterialSlotName": "Material #26",
          "UVChannelData": {
            "bInitialized": true,
            "bOverrideDensities": false,
            "LocalUVDensities": 274.46848,
            "LocalUVDensities": 0.0,
            "LocalUVDensities": 0.0,
            "LocalUVDensities": 0.0
          }
        },
        {
          "MaterialInterface": {
            "ObjectName": "MaterialInstanceConstant'SouthTrim'",
            "ObjectPath": "War/Content/Materials/Environment/Town/SouthTrim.0"
          },
          "MaterialSlotName": "SouthTrim01",
          "ImportedMaterialSlotName": "SouthTrim01",
          "UVChannelData": {
            "bInitialized": true,
            "bOverrideDensities": false,
            "LocalUVDensities": 280.39587,
            "LocalUVDensities": 0.0,
            "LocalUVDensities": 0.0,
            "LocalUVDensities": 0.0
          }
        },
        {
          "MaterialInterface": {
            "ObjectName": "MaterialInstanceConstant'SouthGutter'",
            "ObjectPath": "War/Content/Materials/Environment/Town/SouthGutter.0"
          },
          "MaterialSlotName": "SouthGutter",
          "ImportedMaterialSlotName": "SouthGutter",
          "UVChannelData": {
            "bInitialized": true,
            "bOverrideDensities": false,
            "LocalUVDensities": 140.92163,
            "LocalUVDensities": 0.0,
            "LocalUVDensities": 0.0,
            "LocalUVDensities": 0.0
          }
        }
      ],
      "LightmapUVDensity": 414.96707,
      "LightMapResolution": 64,
      "ExtendedBounds": {
        "Origin": {
          "X": 388.8737,
          "Y": 394.28665,
          "Z": 198.42728
        },
        "BoxExtent": {
          "X": 445.21664,
          "Y": 471.27142,
          "Z": 468.08066
        },
        "SphereRadius": 723.19666
      }
    },
    "BodySetup": {
      "ObjectName": "BodySetup'TownCSmallG2:BodySetup_1'",
      "ObjectPath": "War/Content/Meshes/Environment/Towns/TownCSmallG2.0"
    },
    "NavCollision": {
      "ObjectName": "NavCollision'TownCSmallG2:NavCollision_1'",
      "ObjectPath": "War/Content/Meshes/Environment/Towns/TownCSmallG2.1"
    },
    "LightingGuid": "C8242303-48BEDED2-2E85EE87-79DE4EF0",
    "RenderData": {
      "LODs": [
        {
          "Sections": [
            {
              "MaterialIndex": 3,
              "FirstIndex": 0,
              "NumTriangles": 20,
              "MinVertexIndex": 0,
              "MaxVertexIndex": 31,
              "bEnableCollision": true,
              "bCastShadow": true,
              "bForceOpaque": false,
              "bVisibleInRayTracing": true
            },
            {
              "MaterialIndex": 1,
              "FirstIndex": 60,
              "NumTriangles": 610,
              "MinVertexIndex": 32,
              "MaxVertexIndex": 782,
              "bEnableCollision": true,
              "bCastShadow": true,
              "bForceOpaque": false,
              "bVisibleInRayTracing": true
            },
            {
              "MaterialIndex": 5,
              "FirstIndex": 1890,
              "NumTriangles": 110,
              "MinVertexIndex": 195,
              "MaxVertexIndex": 900,
              "bEnableCollision": true,
              "bCastShadow": true,
              "bForceOpaque": false,
              "bVisibleInRayTracing": true
            },
            {
              "MaterialIndex": 6,
              "FirstIndex": 2220,
              "NumTriangles": 20,
              "MinVertexIndex": 901,
              "MaxVertexIndex": 932,
              "bEnableCollision": true,
              "bCastShadow": true,
              "bForceOpaque": false,
              "bVisibleInRayTracing": true
            },
            {
              "MaterialIndex": 7,
              "FirstIndex": 2280,
              "NumTriangles": 3288,
              "MinVertexIndex": 933,
              "MaxVertexIndex": 6000,
              "bEnableCollision": true,
              "bCastShadow": true,
              "bForceOpaque": false,
              "bVisibleInRayTracing": true
            },
            {
              "MaterialIndex": 8,
              "FirstIndex": 12144,
              "NumTriangles": 96,
              "MinVertexIndex": 6001,
              "MaxVertexIndex": 6192,
              "bEnableCollision": true,
              "bCastShadow": true,
              "bForceOpaque": false,
              "bVisibleInRayTracing": true
            },
            {
              "MaterialIndex": 9,
              "FirstIndex": 12432,
              "NumTriangles": 1018,
              "MinVertexIndex": 6193,
              "MaxVertexIndex": 7264,
              "bEnableCollision": true,
              "bCastShadow": true,
              "bForceOpaque": false,
              "bVisibleInRayTracing": true
            },
            {
              "MaterialIndex": 10,
              "FirstIndex": 15486,
              "NumTriangles": 72,
              "MinVertexIndex": 7265,
              "MaxVertexIndex": 7348,
              "bEnableCollision": true,
              "bCastShadow": true,
              "bForceOpaque": false,
              "bVisibleInRayTracing": true
            },
            {
              "MaterialIndex": 2,
              "FirstIndex": 15702,
              "NumTriangles": 1282,
              "MinVertexIndex": 7349,
              "MaxVertexIndex": 8852,
              "bEnableCollision": true,
              "bCastShadow": true,
              "bForceOpaque": false,
              "bVisibleInRayTracing": true
            },
            {
              "MaterialIndex": 0,
              "FirstIndex": 19548,
              "NumTriangles": 2774,
              "MinVertexIndex": 8853,
              "MaxVertexIndex": 11222,
              "bEnableCollision": true,
              "bCastShadow": true,
              "bForceOpaque": false,
              "bVisibleInRayTracing": true
            },
            {
              "MaterialIndex": 4,
              "FirstIndex": 27870,
              "NumTriangles": 20,
              "MinVertexIndex": 11223,
              "MaxVertexIndex": 11258,
              "bEnableCollision": true,
              "bCastShadow": true,
              "bForceOpaque": false,
              "bVisibleInRayTracing": true
            }
          ],
          "MaxDeviation": 0.0,
          "PositionVertexBuffer": {
            "Stride": 12,
            "NumVertices": 11259
          },
          "VertexBuffer": {
            "NumTexCoords": 3,
            "NumVertices": 11259,
            "Strides": -1,
            "UseHighPrecisionTangentBasis": false,
            "UseFullPrecisionUVs": false
          },
          "ColorVertexBuffer": {
            "Stride": 4,
            "NumVertices": 11259
          }
        }
      ],
      "Bounds": {
        "Origin": {
          "X": 388.8737,
          "Y": 394.28665,
          "Z": 198.42728
        },
        "BoxExtent": {
          "X": 445.21664,
          "Y": 471.27142,
          "Z": 468.08066
        },
        "SphereRadius": 723.19666
      },
      "bLODsShareStaticLighting": true,
      "ScreenSize": [
        0.0,
        0.0,
        0.0,
        0.0,
        0.0,
        0.0,
        0.0,
        0.0
      ]
    }
  }
]