[
  {
    "Type": "SoundAttenuation",
    "Name": "MuffledExplosion",
    "Class": "UScriptClass'SoundAttenuation'",
    "Flags": "RF_Public | RF_Standalone | RF_Transactional | RF_WasLoaded | RF_LoadCompleted",
    "Properties": {
      "Attenuation": {
        "bAttenuateWithLPF": true,
        "bEnableReverbSend": false,
        "LPFRadiusMin": 0.0,
        "LPFRadiusMax": 100.0,
        "LPFFrequencyAtMin": 100.0,
        "LPFFrequencyAtMax": 100.0,
        "HPFFrequencyAtMin": 100.0,
        "HPFFrequencyAtMax": 100.0,
        "DistanceAlgorithm": "EAttenuationDistanceModel::Logarithmic",
        "AttenuationShapeExtents": {
          "X": 4000.0,
          "Y": 0.0,
          "Z": 0.0
        },
        "FalloffDistance": 14000.0
      }
    }
  }
]